apclusterv/__init__.py
apclusterv/cluster_from_prot.py
apclusterv/prepare_from_contig.py
apclusterv/cluster/__init__.py
apclusterv/cluster/adj_ap.py
apclusterv/cluster/apcluster.py
apclusterv/cluster/calscore.py
apclusterv/cluster/ctgconnect.py
apclusterv/cluster/final.py
apclusterv/cluster/mergecluster.py
apclusterv/cluster/runap.py
apclusterv/cluster/runmcl.py
apclusterv/exec/__init__.py
apclusterv/exec/maincluster.py
apclusterv/newscore/__init__.py
apclusterv/newscore/ratiosim.py
apclusterv/scripts/phypertest.R
apclusterv/utils/__init__.py
apclusterv/utils/check.py
apclusterv/utils/protein_mcl.py
apclusterv-1.2.5.dist-info/LICENSE
apclusterv-1.2.5.dist-info/METADATA
apclusterv-1.2.5.dist-info/WHEEL
apclusterv-1.2.5.dist-info/entry_points.txt
apclusterv-1.2.5.dist-info/top_level.txt
apclusterv-1.2.5.dist-info/RECORD
