Metadata-Version: 2.1
Name: apclusterv
Version: 1.2.5
Home-page: https://github.com/hbyaoherbert/Apclusterv.git
Author: haobinherbert
Author-email: haobinherbert@163.com
License: Apache
Classifier: License :: OSI Approved :: GNU General Public License v3 (GPLv3)
Classifier: Natural Language :: English
Classifier: Operating System :: Unix
Classifier: Programming Language :: Python
Classifier: Programming Language :: Python :: 3.8
Classifier: Topic :: Software Development :: Libraries :: Python Modules
Requires-Python: >=3.8
License-File: LICENSE
Requires-Dist: pandas (>=0.18.0)
Requires-Dist: numpy (>=1.9.2)
Requires-Dist: networkx (>=2.8.4)
Requires-Dist: scipy (>=1.8.1)
Requires-Dist: scikit-learn (>=1.1.2)
